{
  "robots": [
    {
      "id": 1,
      "base_xyz": [
        1.0,
        1.0,
        3.071
      ],
      "joint_limits": [
        [
          -180,
          180
        ],
        [
          -90,
          90
        ],
        [
          -90,
          90
        ],
        [
          -180,
          180
        ],
        [
          -90,
          90
        ],
        [
          -90,
          90
        ]
      ],
      "vmax": [
        1.34,
        1.34,
        1.34,
        1.34,
        1.34,
        1.34
      ],
      "amax": [
        2.3,
        2.3,
        2.3,
        2.3,
        2.3,
        2.3
      ],
      "tool_clearance": 0.1
    },
    {
      "id": 2,
      "base_xyz": [
        9.0,
        1.0,
        2.71
      ],
      "joint_limits": [
        [
          -180,
          180
        ],
        [
          -90,
          90
        ],
        [
          -90,
          90
        ],
        [
          -180,
          180
        ],
        [
          -90,
          90
        ],
        [
          -90,
          90
        ]
      ],
      "vmax": [
        1.49,
        1.49,
        1.49,
        1.49,
        1.49,
        1.49
      ],
      "amax": [
        2.73,
        2.73,
        2.73,
        2.73,
        2.73,
        2.73
      ],
      "tool_clearance": 0.1
    }
  ],
  "safe_dist": 0.3,
  "operations": [
    {
      "id": 1,
      "pick_xyz": [
        3.257,
        3.227,
        1.294
      ],
      "place_xyz": [
        1.148,
        1.585,
        3.483
      ],
      "t_hold": 0.75
    },
    {
      "id": 2,
      "pick_xyz": [
        5.258,
        5.014,
        3.592
      ],
      "place_xyz": [
        6.394,
        2.234,
        3.261
      ],
      "t_hold": 0.5
    },
    {
      "id": 3,
      "pick_xyz": [
        6.724,
        5.346,
        3.239
      ],
      "place_xyz": [
        9.17,
        9.241,
        2.876
      ],
      "t_hold": 0.73
    },
    {
      "id": 4,
      "pick_xyz": [
        4.456,
        3.132,
        1.762
      ],
      "place_xyz": [
        9.802,
        2.603,
        4.174
      ],
      "t_hold": 0.5
    },
    {
      "id": 5,
      "pick_xyz": [
        7.532,
        8.836,
        4.043
      ],
      "place_xyz": [
        7.71,
        6.563,
        4.104
      ],
      "t_hold": 1.03
    },
    {
      "id": 6,
      "pick_xyz": [
        3.539,
        9.947,
        4.032
      ],
      "place_xyz": [
        9.256,
        1.622,
        4.04
      ],
      "t_hold": 0.5
    },
    {
      "id": 7,
      "pick_xyz": [
        2.806,
        5.232,
        4.153
      ],
      "place_xyz": [
        4.825,
        3.923,
        3.032
      ],
      "t_hold": 0.82
    },
    {
      "id": 8,
      "pick_xyz": [
        3.007,
        1.378,
        2.745
      ],
      "place_xyz": [
        2.428,
        7.404,
        2.132
      ],
      "t_hold": 0.73
    },
    {
      "id": 9,
      "pick_xyz": [
        8.781,
        8.57,
        1.466
      ],
      "place_xyz": [
        7.893,
        9.738,
        1.974
      ],
      "t_hold": 1.04
    },
    {
      "id": 10,
      "pick_xyz": [
        8.853,
        9.669,
        4.892
      ],
      "place_xyz": [
        5.907,
        5.054,
        3.301
      ],
      "t_hold": 1.17
    },
    {
      "id": 11,
      "pick_xyz": [
        8.357,
        8.102,
        1.578
      ],
      "place_xyz": [
        7.093,
        1.703,
        4.2
      ],
      "t_hold": 0.9
    },
    {
      "id": 12,
      "pick_xyz": [
        1.309,
        9.996,
        2.987
      ],
      "place_xyz": [
        8.735,
        7.449,
        4.153
      ],
      "t_hold": 0.95
    },
    {
      "id": 13,
      "pick_xyz": [
        8.584,
        4.042,
        4.123
      ],
      "place_xyz": [
        1.352,
        8.141,
        3.983
      ],
      "t_hold": 0.6
    },
    {
      "id": 14,
      "pick_xyz": [
        6.451,
        6.363,
        3.072
      ],
      "place_xyz": [
        6.537,
        3.19,
        2.456
      ],
      "t_hold": 1.13
    },
    {
      "id": 15,
      "pick_xyz": [
        1.526,
        8.808,
        2.845
      ],
      "place_xyz": [
        9.743,
        6.875,
        1.206
      ],
      "t_hold": 0.85
    },
    {
      "id": 16,
      "pick_xyz": [
        8.826,
        6.892,
        3.983
      ],
      "place_xyz": [
        1.51,
        4.903,
        1.63
      ],
      "t_hold": 0.73
    },
    {
      "id": 17,
      "pick_xyz": [
        4.435,
        1.342,
        4.591
      ],
      "place_xyz": [
        8.291,
        5.351,
        4.071
      ],
      "t_hold": 0.94
    },
    {
      "id": 18,
      "pick_xyz": [
        1.869,
        5.196,
        1.455
      ],
      "place_xyz": [
        5.818,
        5.553,
        3.744
      ],
      "t_hold": 0.73
    },
    {
      "id": 19,
      "pick_xyz": [
        4.499,
        7.765,
        2.554
      ],
      "place_xyz": [
        9.871,
        9.52,
        4.422
      ],
      "t_hold": 0.62
    },
    {
      "id": 20,
      "pick_xyz": [
        4.053,
        6.411,
        1.593
      ],
      "place_xyz": [
        8.094,
        8.46,
        3.25
      ],
      "t_hold": 0.81
    },
    {
      "id": 21,
      "pick_xyz": [
        3.863,
        8.672,
        4.595
      ],
      "place_xyz": [
        3.638,
        1.564,
        3.107
      ],
      "t_hold": 0.79
    },
    {
      "id": 22,
      "pick_xyz": [
        5.899,
        7.949,
        3.696
      ],
      "place_xyz": [
        2.361,
        7.082,
        3.802
      ],
      "t_hold": 0.67
    },
    {
      "id": 23,
      "pick_xyz": [
        1.975,
        9.474,
        1.638
      ],
      "place_xyz": [
        5.278,
        2.153,
        3.607
      ],
      "t_hold": 0.42
    },
    {
      "id": 24,
      "pick_xyz": [
        2.128,
        8.857,
        1.027
      ],
      "place_xyz": [
        4.423,
        7.741,
        3.775
      ],
      "t_hold": 0.81
    },
    {
      "id": 25,
      "pick_xyz": [
        4.823,
        9.914,
        2.89
      ],
      "place_xyz": [
        8.61,
        3.335,
        3.972
      ],
      "t_hold": 1.19
    },
    {
      "id": 26,
      "pick_xyz": [
        7.3,
        7.977,
        4.187
      ],
      "place_xyz": [
        1.172,
        2.226,
        2.119
      ],
      "t_hold": 1.14
    },
    {
      "id": 27,
      "pick_xyz": [
        9.282,
        6.521,
        2.699
      ],
      "place_xyz": [
        9.759,
        8.41,
        3.099
      ],
      "t_hold": 0.44
    },
    {
      "id": 28,
      "pick_xyz": [
        9.359,
        6.736,
        1.426
      ],
      "place_xyz": [
        5.945,
        2.983,
        2.715
      ],
      "t_hold": 0.98
    },
    {
      "id": 29,
      "pick_xyz": [
        1.792,
        9.485,
        3.456
      ],
      "place_xyz": [
        9.801,
        6.984,
        4.928
      ],
      "t_hold": 0.5
    },
    {
      "id": 30,
      "pick_xyz": [
        8.14,
        5.183,
        3.306
      ],
      "place_xyz": [
        9.892,
        5.764,
        3.902
      ],
      "t_hold": 0.46
    }
  ],
  "space_settings": {
    "width": 10.0,
    "height": 10.0,
    "depth": 5.0,
    "robot_layout": "Сетка (автоматически)"
  }
}