{
  "robots": [
    {
      "id": 1,
      "base_xyz": [
        4.5,
        1.5,
        0.0
      ],
      "joint_limits": [
        [
          -180,
          180
        ],
        [
          -90,
          90
        ],
        [
          -90,
          90
        ],
        [
          -180,
          180
        ],
        [
          -90,
          90
        ],
        [
          -90,
          90
        ]
      ],
      "vmax": [
        1.34,
        1.34,
        1.34,
        1.34,
        1.34,
        1.34
      ],
      "amax": [
        1.53,
        1.53,
        1.53,
        1.53,
        1.53,
        1.53
      ],
      "tool_clearance": 0.1
    },
    {
      "id": 2,
      "base_xyz": [
        2.5,
        2.5,
        0.0
      ],
      "joint_limits": [
        [
          -180,
          180
        ],
        [
          -90,
          90
        ],
        [
          -90,
          90
        ],
        [
          -180,
          180
        ],
        [
          -90,
          90
        ],
        [
          -90,
          90
        ]
      ],
      "vmax": [
        1.14,
        1.14,
        1.14,
        1.14,
        1.14,
        1.14
      ],
      "amax": [
        2.22,
        2.22,
        2.22,
        2.22,
        2.22,
        2.22
      ],
      "tool_clearance": 0.1
    },
    {
      "id": 3,
      "base_xyz": [
        3.5,
        2.5,
        0.0
      ],
      "joint_limits": [
        [
          -180,
          180
        ],
        [
          -90,
          90
        ],
        [
          -90,
          90
        ],
        [
          -180,
          180
        ],
        [
          -90,
          90
        ],
        [
          -90,
          90
        ]
      ],
      "vmax": [
        0.73,
        0.73,
        0.73,
        0.73,
        0.73,
        0.73
      ],
      "amax": [
        1.81,
        1.81,
        1.81,
        1.81,
        1.81,
        1.81
      ],
      "tool_clearance": 0.1
    },
    {
      "id": 4,
      "base_xyz": [
        4.5,
        2.5,
        0.0
      ],
      "joint_limits": [
        [
          -180,
          180
        ],
        [
          -90,
          90
        ],
        [
          -90,
          90
        ],
        [
          -180,
          180
        ],
        [
          -90,
          90
        ],
        [
          -90,
          90
        ]
      ],
      "vmax": [
        1.2,
        1.2,
        1.2,
        1.2,
        1.2,
        1.2
      ],
      "amax": [
        2.76,
        2.76,
        2.76,
        2.76,
        2.76,
        2.76
      ],
      "tool_clearance": 0.1
    },
    {
      "id": 5,
      "base_xyz": [
        7.5,
        2.5,
        0.0
      ],
      "joint_limits": [
        [
          -180,
          180
        ],
        [
          -90,
          90
        ],
        [
          -90,
          90
        ],
        [
          -180,
          180
        ],
        [
          -90,
          90
        ],
        [
          -90,
          90
        ]
      ],
      "vmax": [
        1.1,
        1.1,
        1.1,
        1.1,
        1.1,
        1.1
      ],
      "amax": [
        2.21,
        2.21,
        2.21,
        2.21,
        2.21,
        2.21
      ],
      "tool_clearance": 0.1
    },
    {
      "id": 6,
      "base_xyz": [
        2.5,
        4.5,
        0.0
      ],
      "joint_limits": [
        [
          -180,
          180
        ],
        [
          -90,
          90
        ],
        [
          -90,
          90
        ],
        [
          -180,
          180
        ],
        [
          -90,
          90
        ],
        [
          -90,
          90
        ]
      ],
      "vmax": [
        1.28,
        1.28,
        1.28,
        1.28,
        1.28,
        1.28
      ],
      "amax": [
        2.49,
        2.49,
        2.49,
        2.49,
        2.49,
        2.49
      ],
      "tool_clearance": 0.1
    },
    {
      "id": 7,
      "base_xyz": [
        8.5,
        6.5,
        0.0
      ],
      "joint_limits": [
        [
          -180,
          180
        ],
        [
          -90,
          90
        ],
        [
          -90,
          90
        ],
        [
          -180,
          180
        ],
        [
          -90,
          90
        ],
        [
          -90,
          90
        ]
      ],
      "vmax": [
        0.89,
        0.89,
        0.89,
        0.89,
        0.89,
        0.89
      ],
      "amax": [
        2.7,
        2.7,
        2.7,
        2.7,
        2.7,
        2.7
      ],
      "tool_clearance": 0.1
    },
    {
      "id": 8,
      "base_xyz": [
        7.5,
        7.5,
        0.0
      ],
      "joint_limits": [
        [
          -180,
          180
        ],
        [
          -90,
          90
        ],
        [
          -90,
          90
        ],
        [
          -180,
          180
        ],
        [
          -90,
          90
        ],
        [
          -90,
          90
        ]
      ],
      "vmax": [
        1.37,
        1.37,
        1.37,
        1.37,
        1.37,
        1.37
      ],
      "amax": [
        2.13,
        2.13,
        2.13,
        2.13,
        2.13,
        2.13
      ],
      "tool_clearance": 0.1
    },
    {
      "id": 9,
      "base_xyz": [
        3.5,
        8.5,
        0.0
      ],
      "joint_limits": [
        [
          -180,
          180
        ],
        [
          -90,
          90
        ],
        [
          -90,
          90
        ],
        [
          -180,
          180
        ],
        [
          -90,
          90
        ],
        [
          -90,
          90
        ]
      ],
      "vmax": [
        1.43,
        1.43,
        1.43,
        1.43,
        1.43,
        1.43
      ],
      "amax": [
        2.01,
        2.01,
        2.01,
        2.01,
        2.01,
        2.01
      ],
      "tool_clearance": 0.1
    },
    {
      "id": 10,
      "base_xyz": [
        7.5,
        8.5,
        0.0
      ],
      "joint_limits": [
        [
          -180,
          180
        ],
        [
          -90,
          90
        ],
        [
          -90,
          90
        ],
        [
          -180,
          180
        ],
        [
          -90,
          90
        ],
        [
          -90,
          90
        ]
      ],
      "vmax": [
        0.9,
        0.9,
        0.9,
        0.9,
        0.9,
        0.9
      ],
      "amax": [
        1.68,
        1.68,
        1.68,
        1.68,
        1.68,
        1.68
      ],
      "tool_clearance": 0.1
    }
  ],
  "safe_dist": 0.3,
  "operations": [
    {
      "id": 1,
      "pick_xyz": [
        7.893,
        2.404,
        2.569
      ],
      "place_xyz": [
        7.741,
        4.689,
        3.81
      ],
      "t_hold": 0.75
    },
    {
      "id": 2,
      "pick_xyz": [
        5.837,
        9.218,
        3.833
      ],
      "place_xyz": [
        1.064,
        9.473,
        2.931
      ],
      "t_hold": 0.83
    },
    {
      "id": 3,
      "pick_xyz": [
        9.476,
        9.376,
        1.651
      ],
      "place_xyz": [
        5.384,
        3.029,
        1.078
      ],
      "t_hold": 0.47
    },
    {
      "id": 4,
      "pick_xyz": [
        7.886,
        8.206,
        2.294
      ],
      "place_xyz": [
        6.507,
        5.404,
        2.989
      ],
      "t_hold": 0.62
    },
    {
      "id": 5,
      "pick_xyz": [
        6.601,
        9.042,
        2.853
      ],
      "place_xyz": [
        2.427,
        1.996,
        2.826
      ],
      "t_hold": 0.45
    },
    {
      "id": 6,
      "pick_xyz": [
        6.297,
        4.008,
        3.895
      ],
      "place_xyz": [
        2.664,
        1.201,
        1.087
      ],
      "t_hold": 1.01
    },
    {
      "id": 7,
      "pick_xyz": [
        1.633,
        8.329,
        3.253
      ],
      "place_xyz": [
        2.781,
        6.948,
        3.281
      ],
      "t_hold": 0.95
    },
    {
      "id": 8,
      "pick_xyz": [
        3.982,
        7.974,
        2.176
      ],
      "place_xyz": [
        8.791,
        3.243,
        0.594
      ],
      "t_hold": 0.88
    },
    {
      "id": 9,
      "pick_xyz": [
        6.081,
        9.699,
        3.466
      ],
      "place_xyz": [
        5.929,
        5.165,
        2.906
      ],
      "t_hold": 0.5
    },
    {
      "id": 10,
      "pick_xyz": [
        4.291,
        6.101,
        3.289
      ],
      "place_xyz": [
        3.452,
        2.341,
        1.552
      ],
      "t_hold": 0.84
    },
    {
      "id": 11,
      "pick_xyz": [
        3.771,
        1.904,
        0.609
      ],
      "place_xyz": [
        3.079,
        9.889,
        1.051
      ],
      "t_hold": 0.73
    },
    {
      "id": 12,
      "pick_xyz": [
        6.206,
        6.958,
        1.804
      ],
      "place_xyz": [
        3.352,
        4.037,
        3.509
      ],
      "t_hold": 1.0
    },
    {
      "id": 13,
      "pick_xyz": [
        3.474,
        6.166,
        2.451
      ],
      "place_xyz": [
        2.4,
        7.729,
        0.644
      ],
      "t_hold": 0.57
    },
    {
      "id": 14,
      "pick_xyz": [
        3.45,
        1.849,
        2.87
      ],
      "place_xyz": [
        7.232,
        9.96,
        2.239
      ],
      "t_hold": 1.05
    },
    {
      "id": 15,
      "pick_xyz": [
        9.783,
        9.196,
        1.282
      ],
      "place_xyz": [
        3.539,
        2.477,
        1.576
      ],
      "t_hold": 1.02
    },
    {
      "id": 16,
      "pick_xyz": [
        9.711,
        5.488,
        3.946
      ],
      "place_xyz": [
        9.027,
        7.038,
        3.407
      ],
      "t_hold": 0.83
    },
    {
      "id": 17,
      "pick_xyz": [
        2.888,
        3.602,
        1.097
      ],
      "place_xyz": [
        2.968,
        1.514,
        0.686
      ],
      "t_hold": 0.98
    },
    {
      "id": 18,
      "pick_xyz": [
        3.463,
        5.472,
        2.419
      ],
      "place_xyz": [
        4.531,
        2.826,
        1.296
      ],
      "t_hold": 0.73
    },
    {
      "id": 19,
      "pick_xyz": [
        4.933,
        3.766,
        1.623
      ],
      "place_xyz": [
        1.517,
        7.072,
        1.289
      ],
      "t_hold": 1.17
    },
    {
      "id": 20,
      "pick_xyz": [
        8.147,
        6.995,
        0.687
      ],
      "place_xyz": [
        5.237,
        5.881,
        2.601
      ],
      "t_hold": 0.4
    },
    {
      "id": 21,
      "pick_xyz": [
        6.574,
        4.571,
        0.602
      ],
      "place_xyz": [
        5.121,
        3.789,
        0.164
      ],
      "t_hold": 0.49
    },
    {
      "id": 22,
      "pick_xyz": [
        5.327,
        3.194,
        2.663
      ],
      "place_xyz": [
        4.919,
        2.83,
        0.155
      ],
      "t_hold": 0.8
    },
    {
      "id": 23,
      "pick_xyz": [
        6.851,
        6.875,
        3.122
      ],
      "place_xyz": [
        5.705,
        5.62,
        0.917
      ],
      "t_hold": 1.16
    },
    {
      "id": 24,
      "pick_xyz": [
        2.201,
        5.204,
        3.053
      ],
      "place_xyz": [
        8.994,
        5.617,
        3.011
      ],
      "t_hold": 0.63
    },
    {
      "id": 25,
      "pick_xyz": [
        1.397,
        2.203,
        3.877
      ],
      "place_xyz": [
        3.458,
        1.179,
        1.851
      ],
      "t_hold": 1.2
    },
    {
      "id": 26,
      "pick_xyz": [
        9.371,
        9.727,
        2.84
      ],
      "place_xyz": [
        8.71,
        2.305,
        1.345
      ],
      "t_hold": 1.04
    },
    {
      "id": 27,
      "pick_xyz": [
        5.343,
        7.717,
        3.239
      ],
      "place_xyz": [
        1.138,
        7.829,
        1.733
      ],
      "t_hold": 0.59
    },
    {
      "id": 28,
      "pick_xyz": [
        6.781,
        4.224,
        1.401
      ],
      "place_xyz": [
        4.299,
        7.737,
        3.364
      ],
      "t_hold": 0.65
    },
    {
      "id": 29,
      "pick_xyz": [
        5.449,
        4.968,
        3.513
      ],
      "place_xyz": [
        4.518,
        8.354,
        2.296
      ],
      "t_hold": 0.68
    },
    {
      "id": 30,
      "pick_xyz": [
        5.251,
        4.582,
        0.149
      ],
      "place_xyz": [
        2.519,
        6.54,
        2.955
      ],
      "t_hold": 0.78
    }
  ],
  "space_settings": {
    "width": 10.0,
    "height": 10.0,
    "depth": 5.0,
    "robot_layout": "Шахматное поле (точное размещение)"
  }
}